noteparse/__init__.py
noteparse/configReader.py
noteparse/contentParse.py
noteparse/daily_driver.py
noteparse/dbHelper.py
noteparse/dingTalkMsgHelper.py
noteparse/ossHelper.py
noteparse/playwrightHelper.py
noteparse/projectHelper.py
noteparse/proxyHelper.py
noteparse/requestHelper.py
noteparse-1.1.23.dist-info/LICENSE
noteparse-1.1.23.dist-info/METADATA
noteparse-1.1.23.dist-info/WHEEL
noteparse-1.1.23.dist-info/top_level.txt
noteparse-1.1.23.dist-info/RECORD
