Metadata-Version: 2.1
Name: noteparse
Version: 1.1.23
Summary: a package for parse html to noteinfo
Author: maoyuyan
Author-email: 294567571@qq.com
License: MIT
Platform: all
Classifier: Development Status :: 4 - Beta
Classifier: Intended Audience :: Developers
Classifier: License :: OSI Approved :: MIT License
Classifier: Operating System :: Microsoft :: Windows
Classifier: Natural Language :: Chinese (Simplified)
Classifier: Programming Language :: Python :: 3
Classifier: Topic :: Software Development :: Libraries :: Python Modules
License-File: LICENSE
Requires-Dist: requests>=2.32.3
Requires-Dist: bs4>=0.0.2
Requires-Dist: fastapi>=0.115.4
Requires-Dist: pydantic>=2.7.3
Requires-Dist: loguru>=0.7.2
Requires-Dist: zhipuai>=2.1.5.20230904
Requires-Dist: selenium>=4.21.0
Requires-Dist: fake-useragent>=1.5.1
